streamtranslator/__init__.py
streamtranslator/_streamtranslator.py
streamtranslator/libgcc_s_seh-1.dll
streamtranslator/libstdc++-6.dll
streamtranslator/libwinpthread-1.dll
streamtranslator/streamtranslator.exe
streamtranslator-1.3.0.dist-info/LICENSE
streamtranslator-1.3.0.dist-info/METADATA
streamtranslator-1.3.0.dist-info/WHEEL
streamtranslator-1.3.0.dist-info/top_level.txt
streamtranslator-1.3.0.dist-info/RECORD
