Metadata-Version: 2.1
Name: streamtranslator
Version: 1.3.0
Summary: Real time translation for live streams
Home-page: https://github.com/voicetranslator/voicetranslator
License: UNKNOWN
Project-URL: Documentation, https://github.com/voicetranslator/voicetranslator
Platform: UNKNOWN
Classifier: Development Status :: 5 - Production/Stable
Classifier: Intended Audience :: Developers
Classifier: Programming Language :: Python :: 3
License-File: LICENSE
